odoo/addons/account_analytic_document_date/README.rst
odoo/addons/account_analytic_document_date/__init__.py
odoo/addons/account_analytic_document_date/__manifest__.py
odoo/addons/account_analytic_document_date/hooks.py
odoo/addons/account_analytic_document_date/i18n/account_analytic_document_date.pot
odoo/addons/account_analytic_document_date/i18n/ca.po
odoo/addons/account_analytic_document_date/i18n/es.po
odoo/addons/account_analytic_document_date/i18n/it.po
odoo/addons/account_analytic_document_date/models/__init__.py
odoo/addons/account_analytic_document_date/models/account_analytic_line.py
odoo/addons/account_analytic_document_date/models/account_bank_statement_line.py
odoo/addons/account_analytic_document_date/models/account_move.py
odoo/addons/account_analytic_document_date/models/account_move_line.py
odoo/addons/account_analytic_document_date/readme/CONTRIBUTORS.md
odoo/addons/account_analytic_document_date/readme/DESCRIPTION.md
odoo/addons/account_analytic_document_date/readme/USAGE.md
odoo/addons/account_analytic_document_date/static/description/icon.png
odoo/addons/account_analytic_document_date/static/description/index.html
odoo/addons/account_analytic_document_date/tests/__init__.py
odoo/addons/account_analytic_document_date/tests/test_document_date.py
odoo/addons/account_analytic_document_date/views/account_analytic_line_views.xml
odoo/addons/account_analytic_document_date/views/account_bank_statement_line_views.xml
odoo/addons/account_analytic_document_date/views/account_move.xml
odoo_addon_account_analytic_document_date-17.0.1.0.0.2.dist-info/METADATA
odoo_addon_account_analytic_document_date-17.0.1.0.0.2.dist-info/WHEEL
odoo_addon_account_analytic_document_date-17.0.1.0.0.2.dist-info/top_level.txt
odoo_addon_account_analytic_document_date-17.0.1.0.0.2.dist-info/RECORD
